[{"VIN_number":"1GD21ZCG8CZ695536","Car_brand":"Lexus","Price":"$360115.08","Year_of_model":2010,"First_hand_car":true,"Color":"Maroon","Month":11,"Car_model":"GS"},
{"VIN_number":"3VW517AT8FM675439","Car_brand":"Acura","Price":"$4677.42","Year_of_model":2003,"First_hand_car":false,"Color":"Puce","Month":2,"Car_model":"RL"},
{"VIN_number":"WAUYGBFC5CN970457","Car_brand":"Volkswagen","Price":"$846928.44","Year_of_model":1989,"First_hand_car":true,"Color":"Crimson","Month":10,"Car_model":"Golf"},
{"VIN_number":"1G6DF577280885204","Car_brand":"Dodge","Price":"$619333.83","Year_of_model":1998,"First_hand_car":true,"Color":"Teal","Month":3,"Car_model":"Neon"},
{"VIN_number":"KNALN4D73F5698187","Car_brand":"Scion","Price":"$61254.25","Year_of_model":2006,"First_hand_car":false,"Color":"Orange","Month":8,"Car_model":"xB"},
{"VIN_number":"JTHFE2C27E2030854","Car_brand":"Chevrolet","Price":"$438511.64","Year_of_model":2005,"First_hand_car":false,"Color":"Aquamarine","Month":12,"Car_model":"Impala"},
{"VIN_number":"1FTEW1CW2AK940295","Car_brand":"Chevrolet","Price":"$165980.98","Year_of_model":2006,"First_hand_car":false,"Color":"Purple","Month":8,"Car_model":"Express 1500"},
{"VIN_number":"3C3CFFER0DT659831","Car_brand":"Volkswagen","Price":"$269853.08","Year_of_model":1988,"First_hand_car":true,"Color":"Violet","Month":12,"Car_model":"Fox"},
{"VIN_number":"JN8AE2KP4C9275208","Car_brand":"GMC","Price":"$206935.00","Year_of_model":2012,"First_hand_car":false,"Color":"Orange","Month":5,"Car_model":"Sierra 2500"},
{"VIN_number":"1N6AF0KX3FN921280","Car_brand":"Jaguar","Price":"$766123.95","Year_of_model":2005,"First_hand_car":false,"Color":"Yellow","Month":12,"Car_model":"S-Type"},
{"VIN_number":"WAUUL98EX8A098079","Car_brand":"Chevrolet","Price":"$301212.40","Year_of_model":1995,"First_hand_car":true,"Color":"Teal","Month":9,"Car_model":"Sportvan G20"},
{"VIN_number":"WAUEH74F06N328470","Car_brand":"Dodge","Price":"$632557.32","Year_of_model":1993,"First_hand_car":true,"Color":"Orange","Month":7,"Car_model":"D350 Club"},
{"VIN_number":"SCBZK25E23C808258","Car_brand":"Nissan","Price":"$428431.24","Year_of_model":1994,"First_hand_car":true,"Color":"Goldenrod","Month":11,"Car_model":"300ZX"},
{"VIN_number":"KNAFX5A87E5377374","Car_brand":"Maybach","Price":"$841097.29","Year_of_model":2012,"First_hand_car":false,"Color":"Pink","Month":4,"Car_model":"Landaulet"},
{"VIN_number":"5N1AR2MM1EC275607","Car_brand":"Toyota","Price":"$294707.33","Year_of_model":2001,"First_hand_car":false,"Color":"Khaki","Month":7,"Car_model":"Highlander"},
{"VIN_number":"JM3TB2BV3E0983637","Car_brand":"Aston Martin","Price":"$569476.18","Year_of_model":2011,"First_hand_car":false,"Color":"Mauv","Month":7,"Car_model":"Rapide"},
{"VIN_number":"WBALM7C53EE354426","Car_brand":"Porsche","Price":"$536983.70","Year_of_model":2008,"First_hand_car":true,"Color":"Khaki","Month":11,"Car_model":"Boxster"},
{"VIN_number":"1FTEX1C88AK125677","Car_brand":"Land Rover","Price":"$939158.26","Year_of_model":2002,"First_hand_car":false,"Color":"Khaki","Month":2,"Car_model":"Discovery Series II"},
{"VIN_number":"WBANA73544B018365","Car_brand":"BMW","Price":"$361086.83","Year_of_model":2005,"First_hand_car":true,"Color":"Teal","Month":3,"Car_model":"745"},
{"VIN_number":"WAUSH74FX8N007493","Car_brand":"Mazda","Price":"$744678.50","Year_of_model":2004,"First_hand_car":false,"Color":"Yellow","Month":4,"Car_model":"Tribute"},
{"VIN_number":"KNAFK4A67F5556202","Car_brand":"Hyundai","Price":"$594509.81","Year_of_model":1998,"First_hand_car":true,"Color":"Aquamarine","Month":12,"Car_model":"Sonata"},
{"VIN_number":"WBAEK13486C037418","Car_brand":"Lamborghini","Price":"$304339.73","Year_of_model":2003,"First_hand_car":true,"Color":"Violet","Month":1,"Car_model":"Gallardo"},
{"VIN_number":"WBAWB73557P748181","Car_brand":"Toyota","Price":"$41754.55","Year_of_model":2001,"First_hand_car":false,"Color":"Khaki","Month":7,"Car_model":"Sienna"},
{"VIN_number":"1GD02ZCG1DF772934","Car_brand":"Mitsubishi","Price":"$28692.89","Year_of_model":2002,"First_hand_car":true,"Color":"Goldenrod","Month":11,"Car_model":"Diamante"},
{"VIN_number":"SCFBB03C09G341347","Car_brand":"Eagle","Price":"$453452.54","Year_of_model":1995,"First_hand_car":false,"Color":"Khaki","Month":5,"Car_model":"Vision"},
{"VIN_number":"WBAET37404N720217","Car_brand":"Chevrolet","Price":"$279428.58","Year_of_model":2000,"First_hand_car":false,"Color":"Mauv","Month":1,"Car_model":"Monte Carlo"},
{"VIN_number":"5NPEB4AC8EH161173","Car_brand":"Ford","Price":"$902345.42","Year_of_model":1993,"First_hand_car":true,"Color":"Crimson","Month":3,"Car_model":"F-Series"},
{"VIN_number":"4T1BD1EB5DU163900","Car_brand":"BMW","Price":"$377295.83","Year_of_model":1993,"First_hand_car":false,"Color":"Blue","Month":10,"Car_model":"7 Series"},
{"VIN_number":"WBAUC73529V134417","Car_brand":"Audi","Price":"$744671.11","Year_of_model":1997,"First_hand_car":false,"Color":"Teal","Month":5,"Car_model":"A4"},
{"VIN_number":"1N6BF0KM8FN281089","Car_brand":"Mitsubishi","Price":"$155679.48","Year_of_model":1984,"First_hand_car":false,"Color":"Goldenrod","Month":2,"Car_model":"Mirage"},
{"VIN_number":"SCBFU7ZA5EC382280","Car_brand":"Chevrolet","Price":"$314347.12","Year_of_model":2008,"First_hand_car":true,"Color":"Violet","Month":7,"Car_model":"Cobalt SS"},
{"VIN_number":"WBAWV53577P286802","Car_brand":"BMW","Price":"$747842.35","Year_of_model":2006,"First_hand_car":false,"Color":"Purple","Month":8,"Car_model":"Z4 M"},
{"VIN_number":"SAJWJ0FF7F8212215","Car_brand":"Toyota","Price":"$672669.62","Year_of_model":2003,"First_hand_car":true,"Color":"Turquoise","Month":10,"Car_model":"Corolla"},
{"VIN_number":"1FTWF3C54AE040519","Car_brand":"Chevrolet","Price":"$917878.44","Year_of_model":2004,"First_hand_car":false,"Color":"Maroon","Month":12,"Car_model":"Express 2500"},
{"VIN_number":"1GYS3DEF9BR989848","Car_brand":"Aston Martin","Price":"$113137.37","Year_of_model":2007,"First_hand_car":true,"Color":"Indigo","Month":6,"Car_model":"Vantage"},
{"VIN_number":"JN1AZ4EH9CM019730","Car_brand":"Mitsubishi","Price":"$340506.93","Year_of_model":2006,"First_hand_car":false,"Color":"Maroon","Month":6,"Car_model":"Eclipse"},
{"VIN_number":"WBABN53492J137308","Car_brand":"Mercedes-Benz","Price":"$966526.10","Year_of_model":2005,"First_hand_car":false,"Color":"Yellow","Month":7,"Car_model":"SL-Class"},
{"VIN_number":"1B3CC4FB6AN986385","Car_brand":"Honda","Price":"$730956.46","Year_of_model":1980,"First_hand_car":true,"Color":"Khaki","Month":9,"Car_model":"Civic"},
{"VIN_number":"WBS3U9C58FP535177","Car_brand":"Lotus","Price":"$273762.14","Year_of_model":2006,"First_hand_car":false,"Color":"Red","Month":9,"Car_model":"Elise"},
{"VIN_number":"WAUXG94F49N586647","Car_brand":"Jaguar","Price":"$492771.52","Year_of_model":2008,"First_hand_car":true,"Color":"Maroon","Month":8,"Car_model":"XJ"},
{"VIN_number":"5N3ZA0NCXAN374842","Car_brand":"GMC","Price":"$594118.53","Year_of_model":2006,"First_hand_car":true,"Color":"Violet","Month":11,"Car_model":"Yukon XL"},
{"VIN_number":"WAULH64B81N019739","Car_brand":"BMW","Price":"$787291.69","Year_of_model":2002,"First_hand_car":true,"Color":"Violet","Month":9,"Car_model":"Z8"},
{"VIN_number":"4T3BA3BB9DU965074","Car_brand":"Saab","Price":"$418989.84","Year_of_model":2005,"First_hand_car":false,"Color":"Purple","Month":8,"Car_model":"9-2X"},
{"VIN_number":"WBA3B9C59EJ776371","Car_brand":"Subaru","Price":"$832705.32","Year_of_model":1984,"First_hand_car":true,"Color":"Turquoise","Month":5,"Car_model":"Brat"},
{"VIN_number":"1FMJK1J59AE103011","Car_brand":"Ford","Price":"$741890.07","Year_of_model":1965,"First_hand_car":true,"Color":"Pink","Month":3,"Car_model":"Thunderbird"},
{"VIN_number":"5N1AA0NC4FN021994","Car_brand":"Ford","Price":"$418189.39","Year_of_model":1966,"First_hand_car":false,"Color":"Indigo","Month":6,"Car_model":"Falcon"},
{"VIN_number":"SAJWA4EC7CM458859","Car_brand":"Lexus","Price":"$941966.55","Year_of_model":1995,"First_hand_car":true,"Color":"Crimson","Month":2,"Car_model":"SC"},
{"VIN_number":"WAUBF78E18A893881","Car_brand":"Aston Martin","Price":"$83031.22","Year_of_model":2006,"First_hand_car":false,"Color":"Turquoise","Month":7,"Car_model":"V8 Vantage"},
{"VIN_number":"1FTMF1C80AK826552","Car_brand":"Maserati","Price":"$904708.65","Year_of_model":2004,"First_hand_car":true,"Color":"Maroon","Month":5,"Car_model":"Spyder"},
{"VIN_number":"WA1FFCFS8FR639101","Car_brand":"Infiniti","Price":"$961190.27","Year_of_model":1992,"First_hand_car":true,"Color":"Puce","Month":3,"Car_model":"G"},
{"VIN_number":"KM8JT3AB8CU441171","Car_brand":"Chevrolet","Price":"$890930.48","Year_of_model":2012,"First_hand_car":false,"Color":"Fuscia","Month":12,"Car_model":"Camaro"},
{"VIN_number":"5FPYK1F20AB399563","Car_brand":"Chevrolet","Price":"$360528.78","Year_of_model":2008,"First_hand_car":true,"Color":"Indigo","Month":4,"Car_model":"Cobalt"},
{"VIN_number":"WBA3T3C53F5198160","Car_brand":"Chevrolet","Price":"$532926.82","Year_of_model":2001,"First_hand_car":false,"Color":"Teal","Month":2,"Car_model":"Prizm"},
{"VIN_number":"WBAXH5C57CC080960","Car_brand":"Toyota","Price":"$187849.26","Year_of_model":1996,"First_hand_car":true,"Color":"Yellow","Month":11,"Car_model":"Celica"},
{"VIN_number":"1G6KD57Y61U311239","Car_brand":"Mercury","Price":"$887835.72","Year_of_model":1985,"First_hand_car":false,"Color":"Puce","Month":4,"Car_model":"Topaz"},
{"VIN_number":"NM0KS7ANXAT707710","Car_brand":"Honda","Price":"$854941.47","Year_of_model":2004,"First_hand_car":false,"Color":"Mauv","Month":3,"Car_model":"Accord"},
{"VIN_number":"3GYT4LEF2CG177661","Car_brand":"Kia","Price":"$30066.94","Year_of_model":2002,"First_hand_car":true,"Color":"Teal","Month":10,"Car_model":"Rio"},
{"VIN_number":"WAUBVAFB0BN337926","Car_brand":"GMC","Price":"$599281.16","Year_of_model":2008,"First_hand_car":true,"Color":"Red","Month":12,"Car_model":"Savana 3500"},
{"VIN_number":"3C3CFFJH4DT491074","Car_brand":"Chevrolet","Price":"$921641.02","Year_of_model":1999,"First_hand_car":false,"Color":"Puce","Month":2,"Car_model":"Cavalier"},
{"VIN_number":"WAUCFAFR3AA355163","Car_brand":"Dodge","Price":"$136783.91","Year_of_model":1995,"First_hand_car":false,"Color":"Pink","Month":11,"Car_model":"Viper RT/10"},
{"VIN_number":"WBAWL73518P881924","Car_brand":"Chrysler","Price":"$956647.52","Year_of_model":2000,"First_hand_car":true,"Color":"Crimson","Month":3,"Car_model":"Voyager"},
{"VIN_number":"WAUUL68EX5A218442","Car_brand":"Suzuki","Price":"$940404.77","Year_of_model":2006,"First_hand_car":false,"Color":"Goldenrod","Month":4,"Car_model":"Aerio"},
{"VIN_number":"WBSWD9C53AP654244","Car_brand":"GMC","Price":"$80772.28","Year_of_model":2005,"First_hand_car":false,"Color":"Red","Month":10,"Car_model":"Safari"},
{"VIN_number":"WAUHF98P78A527849","Car_brand":"Scion","Price":"$411428.40","Year_of_model":2008,"First_hand_car":true,"Color":"Red","Month":4,"Car_model":"xD"},
{"VIN_number":"2C3CA4CG8BH658047","Car_brand":"Volkswagen","Price":"$53003.53","Year_of_model":2001,"First_hand_car":true,"Color":"Violet","Month":5,"Car_model":"Eurovan"},
{"VIN_number":"3D73Y3CL0BG231546","Car_brand":"Isuzu","Price":"$9068.91","Year_of_model":1997,"First_hand_car":false,"Color":"Mauv","Month":11,"Car_model":"Rodeo"},
{"VIN_number":"KNADH5A33A6039726","Car_brand":"Jeep","Price":"$511861.72","Year_of_model":1998,"First_hand_car":true,"Color":"Green","Month":11,"Car_model":"Wrangler"},
{"VIN_number":"19UUA76577A144046","Car_brand":"Lexus","Price":"$855995.84","Year_of_model":1991,"First_hand_car":true,"Color":"Purple","Month":12,"Car_model":"ES"},
{"VIN_number":"1G4GC5ER7DF287877","Car_brand":"Chevrolet","Price":"$123497.21","Year_of_model":1989,"First_hand_car":false,"Color":"Violet","Month":5,"Car_model":"Corvette"},
{"VIN_number":"WAUVC58E32A341865","Car_brand":"Volkswagen","Price":"$160610.72","Year_of_model":1992,"First_hand_car":false,"Color":"Yellow","Month":6,"Car_model":"Jetta"},
{"VIN_number":"JN1CV6EK6DM204394","Car_brand":"Acura","Price":"$981901.06","Year_of_model":1999,"First_hand_car":true,"Color":"Crimson","Month":10,"Car_model":"RL"},
{"VIN_number":"1C4RDJDG6DC502167","Car_brand":"BMW","Price":"$778780.15","Year_of_model":2003,"First_hand_car":true,"Color":"Purple","Month":1,"Car_model":"Z8"},
{"VIN_number":"5N1AA0NC7DN024076","Car_brand":"Porsche","Price":"$877659.26","Year_of_model":1988,"First_hand_car":false,"Color":"Mauv","Month":7,"Car_model":"911"},
{"VIN_number":"WVWED7AJ3BW198714","Car_brand":"Cadillac","Price":"$647645.64","Year_of_model":1999,"First_hand_car":true,"Color":"Purple","Month":1,"Car_model":"Seville"},
{"VIN_number":"SCBZK22E61C734828","Car_brand":"Oldsmobile","Price":"$527703.51","Year_of_model":1996,"First_hand_car":false,"Color":"Orange","Month":11,"Car_model":"Bravada"},
{"VIN_number":"3VWKX7AJ1AM653680","Car_brand":"Volkswagen","Price":"$628863.10","Year_of_model":2012,"First_hand_car":true,"Color":"Mauv","Month":2,"Car_model":"Tiguan"},
{"VIN_number":"3GYFNDEY2AS460850","Car_brand":"Ford","Price":"$51055.37","Year_of_model":1999,"First_hand_car":false,"Color":"Puce","Month":1,"Car_model":"Ranger"},
{"VIN_number":"YV4952BZ0E1580574","Car_brand":"Land Rover","Price":"$676904.75","Year_of_model":2010,"First_hand_car":true,"Color":"Maroon","Month":10,"Car_model":"Freelander"},
{"VIN_number":"1G6AD5S39E0095231","Car_brand":"Acura","Price":"$951349.93","Year_of_model":2005,"First_hand_car":false,"Color":"Puce","Month":12,"Car_model":"RSX"},
{"VIN_number":"JH4KA965X2C413735","Car_brand":"BMW","Price":"$48198.75","Year_of_model":2006,"First_hand_car":false,"Color":"Yellow","Month":1,"Car_model":"325"},
{"VIN_number":"1GYS4FEJ8BR958166","Car_brand":"Ford","Price":"$783495.95","Year_of_model":1994,"First_hand_car":true,"Color":"Crimson","Month":6,"Car_model":"Club Wagon"},
{"VIN_number":"3C3CFFDR0DT435105","Car_brand":"Ford","Price":"$527157.15","Year_of_model":2002,"First_hand_car":true,"Color":"Yellow","Month":5,"Car_model":"Econoline E350"},
{"VIN_number":"3C4PDCAB1FT821799","Car_brand":"Oldsmobile","Price":"$983250.05","Year_of_model":1993,"First_hand_car":false,"Color":"Pink","Month":12,"Car_model":"Cutlass Cruiser"},
{"VIN_number":"5N1AR2MM1FC968291","Car_brand":"Isuzu","Price":"$31546.96","Year_of_model":2003,"First_hand_car":true,"Color":"Mauv","Month":6,"Car_model":"Ascender"},
{"VIN_number":"WAUWMAFC8EN037536","Car_brand":"Mercury","Price":"$481936.04","Year_of_model":2010,"First_hand_car":true,"Color":"Crimson","Month":11,"Car_model":"Grand Marquis"},
{"VIN_number":"1FTWW3DY7AE026820","Car_brand":"Hyundai","Price":"$301498.35","Year_of_model":1996,"First_hand_car":true,"Color":"Green","Month":4,"Car_model":"Elantra"},
{"VIN_number":"1G4HR57Y07U487510","Car_brand":"Ford","Price":"$942807.71","Year_of_model":2001,"First_hand_car":false,"Color":"Turquoise","Month":4,"Car_model":"Focus"},
{"VIN_number":"3D73M4HL0BG739347","Car_brand":"Chevrolet","Price":"$20477.69","Year_of_model":1973,"First_hand_car":true,"Color":"Purple","Month":2,"Car_model":"Camaro"},
{"VIN_number":"WBSKG9C57DE029514","Car_brand":"Mazda","Price":"$680921.48","Year_of_model":2000,"First_hand_car":true,"Color":"Pink","Month":1,"Car_model":"Millenia"},
{"VIN_number":"1FTEW1CM6CF725237","Car_brand":"Volkswagen","Price":"$807563.56","Year_of_model":1998,"First_hand_car":false,"Color":"Maroon","Month":9,"Car_model":"rio"},
{"VIN_number":"WAUFFAFL2DA623035","Car_brand":"Mazda","Price":"$854916.58","Year_of_model":1989,"First_hand_car":true,"Color":"Maroon","Month":11,"Car_model":"B-Series"},
{"VIN_number":"3VWML7AJ3DM551516","Car_brand":"Buick","Price":"$913227.27","Year_of_model":2010,"First_hand_car":true,"Color":"Purple","Month":9,"Car_model":"Enclave"},
{"VIN_number":"WAUKF78E78A646803","Car_brand":"Audi","Price":"$171903.01","Year_of_model":2011,"First_hand_car":false,"Color":"Puce","Month":9,"Car_model":"Q7"},
{"VIN_number":"WBAWC33569P507027","Car_brand":"Audi","Price":"$547468.20","Year_of_model":2005,"First_hand_car":false,"Color":"Green","Month":10,"Car_model":"A8"},
{"VIN_number":"JTHBF1D21F5475689","Car_brand":"Lincoln","Price":"$424179.64","Year_of_model":1998,"First_hand_car":false,"Color":"Goldenrod","Month":9,"Car_model":"Town Car"},
{"VIN_number":"WAUKF78EX8A653440","Car_brand":"Chevrolet","Price":"$828015.50","Year_of_model":2002,"First_hand_car":false,"Color":"Orange","Month":8,"Car_model":"Express 1500"},
{"VIN_number":"WAUAH94F26N321854","Car_brand":"BMW","Price":"$695819.91","Year_of_model":2003,"First_hand_car":true,"Color":"Orange","Month":2,"Car_model":"5 Series"},
{"VIN_number":"WAUEF78E38A259484","Car_brand":"Mitsubishi","Price":"$451624.68","Year_of_model":1991,"First_hand_car":false,"Color":"Puce","Month":6,"Car_model":"Galant"},
{"VIN_number":"1G4GB5ER5CF616349","Car_brand":"Ford","Price":"$408842.79","Year_of_model":1999,"First_hand_car":true,"Color":"Goldenrod","Month":2,"Car_model":"F350"},
{"VIN_number":"KNAGM4AD9D5572993","Car_brand":"Ferrari","Price":"$104739.20","Year_of_model":2011,"First_hand_car":true,"Color":"Maroon","Month":6,"Car_model":"458 Italia"}]